MANIFEST.in
README.rst
setup.py
mmm/Reverse_Int.py
mmm/__init__.py
nnn.egg-info/PKG-INFO
nnn.egg-info/SOURCES.txt
nnn.egg-info/dependency_links.txt
nnn.egg-info/requires.txt
nnn.egg-info/top_level.txt